pyfirecrest_helper/__init__.py
pyfirecrest_helper/example.py
pyfirecrest_helper/pyfirecrest_helper.py
pyfirecrest_helper/pyfirecrest_helper.spec
pyfirecrest_helper/secrets.json
pyfirecrest_helper/build/pyfirecrest_helper/Analysis-00.toc
pyfirecrest_helper/build/pyfirecrest_helper/COLLECT-00.toc
pyfirecrest_helper/build/pyfirecrest_helper/EXE-00.toc
pyfirecrest_helper/build/pyfirecrest_helper/PKG-00.toc
pyfirecrest_helper/build/pyfirecrest_helper/PYZ-00.pyz
pyfirecrest_helper/build/pyfirecrest_helper/PYZ-00.toc
pyfirecrest_helper/build/pyfirecrest_helper/base_library.zip
pyfirecrest_helper/build/pyfirecrest_helper/pyfirecrest_helper
pyfirecrest_helper/build/pyfirecrest_helper/pyfirecrest_helper.pkg
pyfirecrest_helper/build/pyfirecrest_helper/warn-pyfirecrest_helper.txt
pyfirecrest_helper/build/pyfirecrest_helper/xref-pyfirecrest_helper.html
pyfirecrest_helper-0.0.1.dist-info/METADATA
pyfirecrest_helper-0.0.1.dist-info/WHEEL
pyfirecrest_helper-0.0.1.dist-info/entry_points.txt
pyfirecrest_helper-0.0.1.dist-info/licenses/LICENSE.md
pyfirecrest_helper-0.0.1.dist-info/RECORD
