Metadata-Version: 2.1
Name: pyfirecrest_helper
Version: 0.0.1
Summary: A small helper package to transfer files via pyFIRECREST api
Project-URL: Homepage, https://juliagustavsenagroscope@dev.azure.com/juliagustavsenagroscope/Allegra_Pilot/_git/pyfirecrest_helper
Author-email: Julia Gustavsen <julia.gustavsen@agroscope.admin.ch>
License-File: LICENSE.md
Classifier: License :: OSI Approved :: GNU General Public License v3 (GPLv3)
Classifier: Operating System :: OS Independent
Classifier: Programming Language :: Python :: 3
Requires-Python: >=3.7
Requires-Dist: hatchling
Requires-Dist: pyfirecrest
Requires-Dist: requests
Requires-Dist: setuptools
